LICENSE
MANIFEST.in
README.md
setup.cfg
setup.py
jinja2_cli_whitespace.egg-info/PKG-INFO
jinja2_cli_whitespace.egg-info/SOURCES.txt
jinja2_cli_whitespace.egg-info/dependency_links.txt
jinja2_cli_whitespace.egg-info/entry_points.txt
jinja2_cli_whitespace.egg-info/not-zip-safe
jinja2_cli_whitespace.egg-info/requires.txt
jinja2_cli_whitespace.egg-info/top_level.txt
jinja2cli/__init__.py
jinja2cli/cli.py
tests/__init__.py
tests/test_jinja2cli.py